prept/__init__.py
prept/__main__.py
prept/boilerplate.py
prept/context.py
prept/engine.py
prept/errors.py
prept/file.py
prept/providers.py
prept/py.typed
prept/utils.py
prept/variables.py
prept/cli/__init__.py
prept/cli/main.py
prept/cli/outputs.py
prept/cli/params.py
prept/cli/status.py
prept/commands/__init__.py
prept/commands/info.py
prept/commands/init.py
prept/commands/install.py
prept/commands/list.py
prept/commands/new.py
prept/commands/uninstall.py
prept-0.2.0.dist-info/licenses/LICENSE
prept-0.2.0.dist-info/METADATA
prept-0.2.0.dist-info/WHEEL
prept-0.2.0.dist-info/entry_points.txt
prept-0.2.0.dist-info/top_level.txt
prept-0.2.0.dist-info/RECORD
