Metadata-Version: 2.4
Name: prept
Version: 0.2.0
Summary: Tool for managing and generating boilerplatesI
Author-email: Izhar Ahmad <thisisizharahmad@gmail.com>
License-Expression: MIT
Project-URL: Homepage, https://prept.rtfd.io
Project-URL: Repository, https://github.com/izxxr/prept
Project-URL: Documentation, https://prept.rtfd.io
Project-URL: Issues, https://github.com/izxxr/prept/issues
Classifier: Development Status :: 4 - Beta
Classifier: Intended Audience :: Developers
Classifier: Natural Language :: English
Classifier: Operating System :: OS Independent
Classifier: Topic :: Internet
Classifier: Topic :: Utilities
Classifier: Topic :: Software Development :: Code Generators
Classifier: Typing :: Typed
Classifier: Programming Language :: Python :: 3.9
Classifier: Programming Language :: Python :: 3.10
Classifier: Programming Language :: Python :: 3.11
Classifier: Programming Language :: Python :: 3.12
Classifier: Programming Language :: Python :: 3.13
Classifier: Programming Language :: Python :: 3.14
Requires-Python: >=3.9
License-File: LICENSE
Requires-Dist: click==8.1.*
Requires-Dist: colorama==0.4.*
Requires-Dist: packaging==25.*
Requires-Dist: pathspec==0.12.*
Requires-Dist: typing_extensions==4.13.*
Provides-Extra: jinja
Requires-Dist: Jinja2>=3.0.0; extra == "jinja"
Dynamic: license-file
